gitsweep/__init__.py
gitsweep/base.py
gitsweep/cli.py
gitsweep/deleter.py
gitsweep/entrypoints.py
gitsweep/inspector.py
gitsweep/scripts/__init__.py
gitsweep/scripts/test.py
gitsweep/tests/__init__.py
gitsweep/tests/test_cli.py
gitsweep/tests/test_deleter.py
gitsweep/tests/test_inspector.py
gitsweep/tests/testcases.py
datopic_git_sweep_latest-0.1.1.dist-info/LICENSE.txt
datopic_git_sweep_latest-0.1.1.dist-info/METADATA
datopic_git_sweep_latest-0.1.1.dist-info/WHEEL
datopic_git_sweep_latest-0.1.1.dist-info/entry_points.txt
datopic_git_sweep_latest-0.1.1.dist-info/top_level.txt
datopic_git_sweep_latest-0.1.1.dist-info/RECORD
