Metadata-Version: 2.1
Name: datopic-git-sweep-latest
Version: 0.1.1
Summary: Clean up branches from your Git remotes
Home-page: http://arc90.com
Author: Arc90, Inc.
Author-email: 
License: MIT
Keywords: git maintenance branches
Classifier: Development Status :: 4 - Beta
Classifier: Environment :: Console
Classifier: License :: OSI Approved :: MIT License
Classifier: Intended Audience :: Developers
Classifier: Natural Language :: English
Classifier: Operating System :: POSIX
Classifier: Programming Language :: Python :: 2.6
Classifier: Programming Language :: Python :: 2.7
Classifier: Programming Language :: Python :: 3
Classifier: Topic :: Software Development :: Quality Assurance
Classifier: Topic :: Software Development :: Version Control
Classifier: Topic :: Text Processing
License-File: LICENSE.txt
Requires-Dist: GitPython (>=0.3.2RC1)
